mutwo/reaper_converters/__init__.py
mutwo/reaper_converters/configurations.py
mutwo/reaper_converters/reaper.py
mutwo/reaper_version/__init__.py
mutwo.reaper-0.5.0.dist-info/LICENSE
mutwo.reaper-0.5.0.dist-info/METADATA
mutwo.reaper-0.5.0.dist-info/WHEEL
mutwo.reaper-0.5.0.dist-info/top_level.txt
mutwo.reaper-0.5.0.dist-info/RECORD
