Metadata-Version: 2.1
Name: mutwo.reaper
Version: 0.5.0
Summary: Reaper extension for event based framework for generative art
Home-page: https://github.com/mutwo-org/mutwo.reaper
Author: Levin Eric Zimmermann
Author-email: levin.eric.zimmermann@posteo.eu
License: GPL
Project-URL: Documentation, https://mutwo-org.github.io
Requires-Python: >=3.9, <4
License-File: LICENSE
Requires-Dist: mutwo.core <3.0.0,>=2.0.0
Provides-Extra: testing
Requires-Dist: pytest >=7.1.1 ; extra == 'testing'
